{
    "version": "2.0.2",
    "description": "Your Universal Control Plane",
    "homepage": "https://crossplane.io",
    "license": "Apache-2.0",
    "architecture": {
        "64bit": {
            "url": "https://releases.crossplane.io/stable/v2.0.2/bin/windows_amd64/crossplane.exe#/kubectl-crossplane.exe",
            "hash": "9eb8cda1c6078d9a262ccccce5324e4c93bb7b0b89f78ab57644b818a87b4c04"
        }
    },
    "bin": "kubectl-crossplane.exe",
    "checkver": {
        "github": "https://github.com/crossplane/crossplane"
    },
    "autoupdate": {
        "architecture": {
            "64bit": {
                "url": "https://releases.crossplane.io/stable/v$version/bin/windows_amd64/crossplane.exe#/kubectl-crossplane.exe"
            }
        }
    }
}
