{
    "version": "26.4.5",
    "description": "Plain-text file markdown note taking with Nextcloud integration",
    "homepage": "https://www.qownnotes.org/",
    "license": "GPL-2.0-only",
    "url": "https://github.com/pbek/QOwnNotes/releases/download/v26.4.5/QOwnNotes.zip",
    "hash": "5fc3da0e4e241421f71493528aed7f9dce5bcf8cb14abe0864b97ea542c4d08d",
    "bin": [
        "QOwnNotes.exe",
        "QOwnNotesPortable.bat"
    ],
    "shortcuts": [
        [
            "QOwnNotes.exe",
            "QOwnNotes"
        ]
    ],
    "persist": "Data",
    "checkver": {
        "github": "https://github.com/pbek/QOwnNotes"
    },
    "autoupdate": {
        "url": "https://github.com/pbek/QOwnNotes/releases/download/v$version/QOwnNotes.zip"
    }
}
