{
    "version": "25.5.7",
    "description": "Plain-text file markdown note taking with Nextcloud integration",
    "homepage": "https://www.qownnotes.org/",
    "license": "GPL-2.0-only",
    "url": "https://github.com/pbek/QOwnNotes/releases/download/v25.5.7/QOwnNotes.zip",
    "hash": "ab4f2f3b649d7f01a07ee87813a999a683af4927f997a7070acf5bdb905c2972",
    "bin": [
        "QOwnNotes.exe",
        "QOwnNotesPortable.bat"
    ],
    "shortcuts": [
        [
            "QOwnNotes.exe",
            "QOwnNotes"
        ]
    ],
    "persist": "Data",
    "checkver": {
        "github": "https://github.com/pbek/QOwnNotes"
    },
    "autoupdate": {
        "url": "https://github.com/pbek/QOwnNotes/releases/download/v$version/QOwnNotes.zip"
    }
}
