{
    "version": "1.1.1",
    "description": "Fully featured and highly configurable SFTP server with optional FTP/S and WebDAV support.",
    "homepage": "https://github.com/drakkan/sftpgo",
    "url": "https://github.com/drakkan/sftpgo/releases/download/v1.1.1/sftpgo_v1.1.1_windows_portable_x86_64.zip",
    "hash": "303e99f1b0d51aa702d146ae2e2f18c50d564fef6f9182cd4c877328b4f98625",
    "bin": "sftpgo.exe",
    "checkver": "github",
    "autoupdate": {
        "url": "https://github.com/drakkan/sftpgo/releases/download/v$version/sftpgo_v$version_windows_portable_x86_64.zip"
    }
}
