{
    "version": "1.8.3",
    "description": "talosctl is a CLI tool which interfaces with the Talos API in an easy manner.",
    "homepage": "https://www.talos.dev",
    "license": "MPL-2.0",
    "architecture": {
        "64bit": {
            "url": "https://github.com/siderolabs/talos/releases/download/v1.8.3/talosctl-windows-amd64.exe#/talosctl.exe",
            "hash": "sha512:bd102100b56002499ca605a93210a094ad0fa737ad8fe20227eca05073533dc6d93891cf8e8d151ab2030184c661262435e1811f3d5fd1648e240659ae4dba37"
        }
    },
    "bin": "talosctl.exe",
    "checkver": {
        "github": "https://github.com/siderolabs/talos"
    },
    "autoupdate": {
        "architecture": {
            "64bit": {
                "url": "https://github.com/siderolabs/talos/releases/download/v$version/talosctl-windows-amd64.exe#/talosctl.exe"
            }
        },
        "hash": {
            "url": "$baseurl/sha512sum.txt"
        }
    }
}
